{
    "Data": {
        "3009": {
            "TrackName": [
                "Animation Track",
                "0"
            ],
            "npcID": [
                10028
            ],
            "TrackType": [
                2
            ],
            "id": 3009,
            "Name": 12015,
            "Path": "W1_Area_15_ForBuild_02"
        },
        "3010": {
            "TrackName": [
                "Animation Track (1)"
            ],
            "npcID": [
                10027
            ],
            "TrackType": [
                2
            ],
            "id": 3010,
            "Name": 10010,
            "Path": "T1_Area_09_ForBuild_04"
        },
        "3011": {
            "TrackName": [
                "Animation Track"
            ],
            "npcID": [
                10031
            ],
            "TrackType": [
                2
            ],
            "id": 3011,
            "Name": 13101,
            "Path": "W2_Area_r1_ForBuild_01"
        },
        "3019": {
            "TrackName": [
                "Animation Track (1)",
                "0"
            ],
            "npcID": [
                10056
            ],
            "TrackType": [
                2
            ],
            "id": 3019,
            "Name": 10023,
            "Path": "T1_Area_22_ForBuild_03"
        },
        "3018": {
            "TrackName": [
                "Animation Track",
                "Transform Event Track (1)"
            ],
            "npcID": [
                10060,
                10060
            ],
            "TrackType": [
                2,
                2
            ],
            "id": 3018,
            "Name": 14018,
            "Path": "W2_Area_n18_ForBuild_01"
        },
        "3014": {
            "TrackName": [
                "Animation Track",
                "0"
            ],
            "npcID": [
                10034
            ],
            "TrackType": [
                2
            ],
            "id": 3014,
            "Name": 13012,
            "Path": "W2_Area_12_ForBuild_01"
        },
        "3015": {
            "TrackName": [
                "Animation Track",
                "0"
            ],
            "npcID": [
                10045
            ],
            "TrackType": [
                2
            ],
            "id": 3015,
            "Name": 13015,
            "Path": "W2_Area_15_ForBuild_01"
        },
        "3016": {
            "TrackName": [
                "Animation Track (3)"
            ],
            "npcID": [
                10046
            ],
            "TrackType": [
                2
            ],
            "id": 3016,
            "Name": 13004,
            "Path": "W2_Area_04_ForBuild_01"
        },
        "3001": {
            "TrackName": [
                "Animation Track"
            ],
            "npcID": [
                10016
            ],
            "TrackType": [
                2
            ],
            "id": 3001,
            "Name": 12002,
            "Path": "W1_Area_02_ForBuild_02"
        },
        "3002": {
            "TrackName": [
                "Animation Track"
            ],
            "npcID": [
                10017
            ],
            "TrackType": [
                2
            ],
            "id": 3002,
            "Name": 12005,
            "Path": "W1_Area_05_ForBuild_01"
        },
        "3003": {
            "TrackName": [
                "Animation Track"
            ],
            "npcID": [
                10001
            ],
            "TrackType": [
                2
            ],
            "id": 3003,
            "Name": 10005,
            "Path": "T1_Area_08_ForBuild_02"
        },
        "3004": {
            "TrackName": [
                "Animation Track",
                "Transform Event Track"
            ],
            "npcID": [
                10023,
                10023
            ],
            "TrackType": [
                2,
                2
            ],
            "id": 3004,
            "Name": 12024,
            "Path": "W1_Area_24_ForBuild_02"
        },
        "3005": {
            "TrackName": [
                "Animation Track"
            ],
            "npcID": [
                10005
            ],
            "TrackType": [
                2
            ],
            "id": 3005,
            "Name": 12018,
            "Path": "W1_Area_18_ForBuild_01"
        },
        "3006": {
            "TrackName": [
                "Animation Track",
                "Transform Event Track"
            ],
            "npcID": [
                10001,
                10001
            ],
            "TrackType": [
                2,
                2
            ],
            "id": 3006,
            "Name": 10005,
            "Path": "T1_Area_08_ForBuild_03"
        },
        "3017": {
            "TrackName": [
                "Animation Track",
                "0"
            ],
            "npcID": [
                10038
            ],
            "TrackType": [
                2
            ],
            "id": 3017,
            "Name": 13030,
            "Path": "W2_Area_30_ForBuild_02"
        }
    },
    "AllIds": [
        3001,
        3002,
        3003,
        3004,
        3005,
        3006,
        3009,
        3010,
        3011,
        3014,
        3015,
        3016,
        3017,
        3018,
        3019
    ]
}