{
    "AllIds": [
        31007,
        31010,
        31013,
        31016,
        31019,
        35026,
        70002,
        70003,
        79001,
        79002,
        79003,
        79004
    ],
    "Data": {
        "31010": {
            "id": 31010,
            "Num": 10
        },
        "70003": {
            "id": 70003,
            "Num": 1
        },
        "31013": {
            "id": 31013,
            "Num": 10
        },
        "79003": {
            "id": 79003,
            "Num": 5
        },
        "31016": {
            "id": 31016,
            "Num": 10
        },
        "79001": {
            "id": 79001,
            "Num": 15
        },
        "79002": {
            "id": 79002,
            "Num": 10
        },
        "31019": {
            "id": 31019,
            "Num": 10
        },
        "79004": {
            "id": 79004,
            "Num": 1
        },
        "70002": {
            "id": 70002,
            "Num": 2
        },
        "35026": {
            "id": 35026,
            "Num": 10
        },
        "31007": {
            "id": 31007,
            "Num": 10
        }
    }
}