{
    "Data": [
        {
            "sort": 1,
            "nameid": 1067,
            "id": 1
        },
        {
            "sort": 2,
            "nameid": 1068,
            "id": 2
        },
        {
            "sort": 3,
            "nameid": 1069,
            "id": 3
        },
        {
            "sort": 4,
            "nameid": 1070,
            "id": 4
        },
        {
            "sort": 5,
            "nameid": 1071,
            "id": 5
        }
    ],
    "AllIds": [
        1,
        2,
        3,
        4,
        5
    ]
}