{
    "Data": {
        "501760": {
            "id": 501760,
            "text": "명중률"
        },
        "501761": {
            "id": 501761,
            "text": "질서 에너지"
        },
        "501762": {
            "id": 501762,
            "text": "혼돈 에너지"
        },
        "501763": {
            "id": 501763,
            "text": "피해 스킬 효과 증가"
        },
        "501764": {
            "id": 501764,
            "text": "회복 스킬 효과 증가"
        },
        "501765": {
            "id": 501765,
            "text": "1회 스킬 피해"
        },
        "501766": {
            "id": 501766,
            "text": "질서 에너지 소모"
        },
        "501767": {
            "id": 501767,
            "text": "혼돈 에너지 소모"
        },
        "501768": {
            "id": 501768,
            "text": "버프 제거 수량"
        },
        "501769": {
            "id": 501769,
            "text": "몬스터 유형"
        },
        "501770": {
            "id": 501770,
            "text": "실드"
        },
        "501771": {
            "id": 501771,
            "text": "연격 포인트"
        },
        "501772": {
            "id": 501772,
            "text": "쿨타임 단축"
        },
        "501773": {
            "id": 501773,
            "text": "패시브 스킬 적용"
        },
        "501774": {
            "id": 501774,
            "text": "디버프 상태 포함 여부"
        },
        "501775": {
            "id": 501775,
            "text": "질서 에너지 소모 감소"
        },
        "501776": {
            "id": 501776,
            "text": "혼돈 에너지 소모 감소"
        },
        "501777": {
            "id": 501777,
            "text": "보스 연격 포인트"
        },
        "501778": {
            "id": 501778,
            "text": "치명타 레벨"
        },
        "501779": {
            "id": 501779,
            "text": "치명타 피해 레벨"
        },
        "501780": {
            "id": 501780,
            "text": "버프 스택수"
        },
        "501781": {
            "id": 501781,
            "text": "치유량"
        },
        "501782": {
            "id": 501782,
            "text": "질서 에너지 획득 속도"
        },
        "501783": {
            "id": 501783,
            "text": "공격 비율"
        },
        "501784": {
            "id": 501784,
            "text": "물리 방어 비율"
        },
        "501785": {
            "id": 501785,
            "text": "마법 방어 비율"
        },
        "501786": {
            "id": 501786,
            "text": "HP 비율"
        },
        "501787": {
            "id": 501787,
            "text": "HP 증가"
        },
        "501788": {
            "id": 501788,
            "text": "공격 증가"
        },
        "501789": {
            "id": 501789,
            "text": "물리 방어 증가"
        },
        "501790": {
            "id": 501790,
            "text": "마법 방어 증가"
        },
        "501791": {
            "id": 501791,
            "text": "중지"
        },
        "501792": {
            "id": 501792,
            "text": "제거"
        },
        "501793": {
            "id": 501793,
            "text": "정화"
        },
        "501794": {
            "id": 501794,
            "text": "에너지 회득"
        },
        "501795": {
            "id": 501795,
            "text": "부활"
        },
        "501796": {
            "id": 501796,
            "text": "강화"
        },
        "501797": {
            "id": 501797,
            "text": "피해 감소"
        },
        "501798": {
            "id": 501798,
            "text": "암살"
        },
        "501799": {
            "id": 501799,
            "text": "물리 단일"
        },
        "501800": {
            "id": 501800,
            "text": "물리 단체"
        },
        "501801": {
            "id": 501801,
            "text": "물리 방어"
        },
        "501802": {
            "id": 501802,
            "text": "마법 단일"
        },
        "501803": {
            "id": 501803,
            "text": "마법 단체"
        },
        "501804": {
            "id": 501804,
            "text": "마법 방어"
        },
        "501805": {
            "id": 501805,
            "text": "수호형"
        },
        "501806": {
            "id": 501806,
            "text": "파괴형"
        },
        "501807": {
            "id": 501807,
            "text": "암살형"
        },
        "501808": {
            "id": 501808,
            "text": "방해형"
        },
        "501809": {
            "id": 501809,
            "text": "회복형"
        },
        "501810": {
            "id": 501810,
            "text": "마도형"
        },
        "501811": {
            "id": 501811,
            "text": "마녀"
        },
        "501812": {
            "id": 501812,
            "text": "생존 능력이 뛰어난 인형"
        },
        "501813": {
            "id": 501813,
            "text": "정면돌파를 두려워하지 않는 인형"
        },
        "501814": {
            "id": 501814,
            "text": "뒤 열에 적에게 여러 번의 물리 피해를 입히는 인형"
        },
        "501815": {
            "id": 501815,
            "text": "각종 버프와 디버프를 사용하는 인형"
        },
        "501816": {
            "id": 501816,
            "text": "팀원을 회복시키는 능력을 갖춘 인형"
        },
        "501817": {
            "id": 501817,
            "text": "다양한 마법으로 공격하는 인형"
        },
        "501818": {
            "id": 501818,
            "text": "미지의 마법을 습득한 신비한 유형"
        },
        "501827": {
            "id": 501827,
            "text": "레벨"
        },
        "501828": {
            "id": 501828,
            "text": "레어도"
        },
        "501829": {
            "id": 501829,
            "text": "획득 순서"
        },
        "501830": {
            "id": 501830,
            "text": "HP"
        },
        "501831": {
            "id": 501831,
            "text": "SSR"
        },
        "501832": {
            "id": 501832,
            "text": "SR"
        },
        "501833": {
            "id": 501833,
            "text": "R"
        },
        "501834": {
            "id": 501834,
            "text": "UR"
        },
        "501835": {
            "id": 501835,
            "text": "물리 회피율"
        },
        "501836": {
            "id": 501836,
            "text": "레어도:"
        },
        "501837": {
            "id": 501837,
            "text": "유형:"
        },
        "501838": {
            "id": 501838,
            "text": "스킬 유형:"
        },
        "501839": {
            "id": 501839,
            "text": "마법 피해 스킬"
        },
        "501840": {
            "id": 501840,
            "text": "물리 피해 스킬"
        },
        "501841": {
            "id": 501841,
            "text": "치료 스킬"
        },
        "501842": {
            "id": 501842,
            "text": "보조 스킬"
        },
        "501852": {
            "id": 501852,
            "text": "받는 최대 물리 피해"
        },
        "501853": {
            "id": 501853,
            "text": "마력 본능 효과 증가"
        },
        "501854": {
            "id": 501854,
            "text": "생존 마스터 효과 증가"
        },
        "501855": {
            "id": 501855,
            "text": "위치 이탈 효과 증가"
        },
        "501856": {
            "id": 501856,
            "text": "공격 마스터 효과 증가"
        },
        "501857": {
            "id": 501857,
            "text": "방어 마스터 효과 증가"
        },
        "501858": {
            "id": 501858,
            "text": "어둠의 계약 효과 증가"
        },
        "501859": {
            "id": 501859,
            "text": "마법 방어 마스터 효과 증가"
        },
        "501860": {
            "id": 501860,
            "text": "회복 마스터 효과 증가"
        },
        "501864": {
            "id": 501864,
            "text": "속도 마스터 효과 증가"
        },
        "501865": {
            "id": 501865,
            "text": "성령의 빛 효과 증가"
        },
        "501866": {
            "id": 501866,
            "text": "혼미 효과 증가"
        },
        "501867": {
            "id": 501867,
            "text": "영계의 비호 효과 증가"
        },
        "501868": {
            "id": 501868,
            "text": "꽃의 드레스 효과 증가"
        },
        "501869": {
            "id": 501869,
            "text": "전주곡 효과 증가"
        },
        "501870": {
            "id": 501870,
            "text": "행복의 현 효과 증가"
        },
        "501871": {
            "id": 501871,
            "text": "선율의 강화 효과 증가"
        },
        "501872": {
            "id": 501872,
            "text": "전의 폭발 효과 증가"
        },
        "501873": {
            "id": 501873,
            "text": "성수의 영광 효과 증가"
        },
        "501874": {
            "id": 501874,
            "text": "성수의 가호 효과 증가"
        },
        "501875": {
            "id": 501875,
            "text": "영혼 인장3 효과 상승"
        },
        "501876": {
            "id": 501876,
            "text": "통찰 효과 증가"
        },
        "501877": {
            "id": 501877,
            "text": "별의 축복 효과 증가"
        },
        "501878": {
            "id": 501878,
            "text": "검의 영역 효과 증가"
        },
        "501879": {
            "id": 501879,
            "text": "암살 테크닉 효과 증가"
        },
        "501880": {
            "id": 501880,
            "text": "서리의 육신 효과 증가"
        },
        "501882": {
            "id": 501882,
            "text": "용의 분노 효과 증가"
        },
        "501883": {
            "id": 501883,
            "text": "용의 역린 효과 증가"
        },
        "501884": {
            "id": 501884,
            "text": "용의 춤 효과 증가"
        },
        "501885": {
            "id": 501885,
            "text": "이별의 고통 효과 증가"
        },
        "501886": {
            "id": 501886,
            "text": "물리 방어 효과 증가"
        },
        "501887": {
            "id": 501887,
            "text": "공명의 꿈 효과 증가"
        },
        "501888": {
            "id": 501888,
            "text": "영혼 속박 효과 증가"
        },
        "501889": {
            "id": 501889,
            "text": "배수진 효과 증가"
        },
        "501890": {
            "id": 501890,
            "text": "악마의 힘 효과 증가"
        },
        "501891": {
            "id": 501891,
            "text": "지옥의 소리 효과 증가"
        },
        "501892": {
            "id": 501892,
            "text": "영원의 빛 효과 증가"
        },
        "501893": {
            "id": 501893,
            "text": "궤변의 대가 효과 증가"
        },
        "501894": {
            "id": 501894,
            "text": "공명정대 효과 증가"
        },
        "501895": {
            "id": 501895,
            "text": "비정 효과 증가"
        },
        "501896": {
            "id": 501896,
            "text": "핏빛 가무 효과 증가"
        },
        "501897": {
            "id": 501897,
            "text": "자가복구 효과 증가"
        },
        "501898": {
            "id": 501898,
            "text": "재건 효과 증가"
        },
        "501899": {
            "id": 501899,
            "text": "순풍의 화살 효과 증가"
        },
        "501900": {
            "id": 501900,
            "text": "약점 간파 효과 증가"
        },
        "501901": {
            "id": 501901,
            "text": "왕정의 바람 효과 증가"
        },
        "501902": {
            "id": 501902,
            "text": "점지 효과 증가"
        },
        "501903": {
            "id": 501903,
            "text": "예지 효과 증가"
        },
        "501904": {
            "id": 501904,
            "text": "사냥 본능 효과 증가"
        },
        "501905": {
            "id": 501905,
            "text": "고통을 즐기는 자 효과 증가"
        },
        "501906": {
            "id": 501906,
            "text": "본성 각성 효과 증가"
        },
        "501907": {
            "id": 501907,
            "text": "갈구 효과 증가"
        },
        "501908": {
            "id": 501908,
            "text": "점유욕 효과 증가"
        },
        "501909": {
            "id": 501909,
            "text": "화려 효과 증가"
        },
        "501910": {
            "id": 501910,
            "text": "빛의 선율 효과 증가"
        },
        "501911": {
            "id": 501911,
            "text": "찬란 효과 증가"
        },
        "501912": {
            "id": 501912,
            "text": "우울 가면 효과 증가"
        },
        "501913": {
            "id": 501913,
            "text": "영혼 가면 효과 증가"
        },
        "501914": {
            "id": 501914,
            "text": "진혼곡 효과 증가"
        },
        "501915": {
            "id": 501915,
            "text": "마비 효과 증가"
        },
        "501916": {
            "id": 501916,
            "text": "극독 효과 증가"
        },
        "501917": {
            "id": 501917,
            "text": "어둠의 연회 효과 증가"
        },
        "501918": {
            "id": 501918,
            "text": "아리아 효과 증가"
        },
        "501919": {
            "id": 501919,
            "text": "신관의 축복 효과 증가"
        },
        "501920": {
            "id": 501920,
            "text": "거룩한 마음 효과 증가"
        },
        "501921": {
            "id": 501921,
            "text": "마법 방어 효과 증가"
        },
        "501923": {
            "id": 501923,
            "text": "땅의 은혜 효과 증가"
        },
        "501924": {
            "id": 501924,
            "text": "밤의 저주 효과 증가"
        },
        "501925": {
            "id": 501925,
            "text": "명계의 힘 효과 증가"
        },
        "501926": {
            "id": 501926,
            "text": "불길한 밤 효과 증가"
        },
        "501927": {
            "id": 501927,
            "text": "부식 효과 증가"
        },
        "501929": {
            "id": 501929,
            "text": "공평한 치유 효과 증가"
        },
        "501930": {
            "id": 501930,
            "text": "밤의 일족 효과 증가"
        },
        "501931": {
            "id": 501931,
            "text": "금기 효과 증가"
        },
        "501932": {
            "id": 501932,
            "text": "치유의 마음 효과 증가"
        },
        "501933": {
            "id": 501933,
            "text": "해신의 축복 효과 증가"
        },
        "501934": {
            "id": 501934,
            "text": "꿈을 찾아 효과 증가"
        },
        "501935": {
            "id": 501935,
            "text": "만조와 간조 효과 증가"
        },
        "501936": {
            "id": 501936,
            "text": "자연의 소리 효과 증가"
        },
        "501937": {
            "id": 501937,
            "text": "메아리 효과 증가"
        },
        "501938": {
            "id": 501938,
            "text": "신의 허락 효과 증가"
        },
        "501939": {
            "id": 501939,
            "text": "명상 효과 증가"
        },
        "501940": {
            "id": 501940,
            "text": "태양의 후예 효과 증가"
        },
        "501941": {
            "id": 501941,
            "text": "멸혼의 불꽃 효과 증가"
        },
        "501942": {
            "id": 501942,
            "text": "열반 효과 증가"
        },
        "501943": {
            "id": 501943,
            "text": "구슬 축복 효과 증가"
        },
        "501944": {
            "id": 501944,
            "text": "고난 극복 효과 증가"
        },
        "501945": {
            "id": 501945,
            "text": "숲의 가호 효과 증가"
        },
        "501946": {
            "id": 501946,
            "text": "자연의 법칙 효과 증가"
        },
        "501947": {
            "id": 501947,
            "text": "단일 치료"
        },
        "501948": {
            "id": 501948,
            "text": "단체 치료"
        },
        "501949": {
            "id": 501949,
            "text": "약화"
        },
        "501950": {
            "id": 501950,
            "text": "HP 강화Ⅰ 기본 최대 HP +2%"
        },
        "501951": {
            "id": 501951,
            "text": "HP 강화Ⅱ 기본 최대 HP +3%"
        },
        "501952": {
            "id": 501952,
            "text": "공격 강화Ⅰ 기본 공격력 +2%"
        },
        "501953": {
            "id": 501953,
            "text": "공격 강화Ⅱ 기본 공격력 +3%"
        },
        "501954": {
            "id": 501954,
            "text": "물리 방어 강화Ⅰ 기본 물리 방어 +2%"
        },
        "501955": {
            "id": 501955,
            "text": "물리 방어 강화Ⅱ 기본 물리 방어 +3%"
        },
        "501956": {
            "id": 501956,
            "text": "마법 방어 강화Ⅰ 기본 마법 방어 +2%"
        },
        "501957": {
            "id": 501957,
            "text": "마법 방어 강화Ⅱ 기본 마법 방어 +3%"
        },
        "502377": {
            "id": 502377,
            "text": "폭발"
        },
        "502378": {
            "id": 502378,
            "text": "받는 최대 마법 피해"
        },
        "502379": {
            "id": 502379,
            "text": "받는 피해 최대 발동 확률"
        },
        "502380": {
            "id": 502380,
            "text": "기본 코스튬"
        },
        "502381": {
            "id": 502381,
            "text": "캠퍼스의 추억"
        },
        "502382": {
            "id": 502382,
            "text": "축복의 연회"
        },
        "502383": {
            "id": 502383,
            "text": "짙푸른 바다"
        },
        "502384": {
            "id": 502384,
            "text": "백사장에서의 휴일"
        },
        "502816": {
            "id": 502816,
            "text": ""
        },
        "502815": {
            "id": 502815,
            "text": ""
        },
        "502814": {
            "id": 502814,
            "text": ""
        },
        "502813": {
            "id": 502813,
            "text": ""
        },
        "502812": {
            "id": 502812,
            "text": ""
        },
        "502811": {
            "id": 502811,
            "text": ""
        },
        "502810": {
            "id": 502810,
            "text": ""
        },
        "502809": {
            "id": 502809,
            "text": ""
        },
        "502808": {
            "id": 502808,
            "text": ""
        },
        "502807": {
            "id": 502807,
            "text": ""
        },
        "502806": {
            "id": 502806,
            "text": ""
        },
        "502805": {
            "id": 502805,
            "text": ""
        },
        "502804": {
            "id": 502804,
            "text": ""
        },
        "502803": {
            "id": 502803,
            "text": ""
        },
        "502802": {
            "id": 502802,
            "text": ""
        },
        "502801": {
            "id": 502801,
            "text": ""
        },
        "502800": {
            "id": 502800,
            "text": ""
        },
        "502799": {
            "id": 502799,
            "text": ""
        },
        "502798": {
            "id": 502798,
            "text": ""
        },
        "502797": {
            "id": 502797,
            "text": "Tian"
        },
        "502796": {
            "id": 502796,
            "text": "门徒"
        },
        "502795": {
            "id": 502795,
            "text": "美和野らぐ"
        },
        "502794": {
            "id": 502794,
            "text": "ピナケス"
        },
        "502793": {
            "id": 502793,
            "text": "Nekojira"
        },
        "502792": {
            "id": 502792,
            "text": "Angye"
        },
        "502791": {
            "id": 502791,
            "text": "Namie"
        },
        "502790": {
            "id": 502790,
            "text": "Lirica"
        },
        "502789": {
            "id": 502789,
            "text": "ツナ"
        },
        "502788": {
            "id": 502788,
            "text": "じゅうはち"
        },
        "502787": {
            "id": 502787,
            "text": "irvineQ"
        },
        "502786": {
            "id": 502786,
            "text": "돌파3 오픈"
        },
        "502785": {
            "id": 502785,
            "text": "돌파2 오픈"
        },
        "502784": {
            "id": 502784,
            "text": "난나르가 곤히 잠들 때마다, 귀여운 잠꼬대를 한다.$B$아…… 거울에 새로운 모습이 비쳐요……"
        },
        "502783": {
            "id": 502783,
            "text": "흔치 않은 휴일, 네메시가 나른하게 소파에 누워있다.$B$\"넌 왜 온 거지, 쉬는 날일 텐데?\""
        },
        "502782": {
            "id": 502782,
            "text": "꿈"
        },
        "502781": {
            "id": 502781,
            "text": "고요한 휴일"
        },
        "502585": {
            "id": 502585,
            "text": "AIKO"
        },
        "502779": {
            "id": 502779,
            "text": "테스트용 이름"
        },
        "502778": {
            "id": 502778,
            "text": "원소: "
        },
        "502777": {
            "id": 502777,
            "text": "원소 버프"
        },
        "502776": {
            "id": 502776,
            "text": "6개의 동일 원소 속성 인형 출전 및 예비 배치"
        },
        "502775": {
            "id": 502775,
            "text": "3개의 동일 원소 속성 인형 출전"
        },
        "502774": {
            "id": 502774,
            "text": "에테르"
        },
        "502773": {
            "id": 502773,
            "text": "유황불"
        },
        "502772": {
            "id": 502772,
            "text": "염석"
        },
        "502771": {
            "id": 502771,
            "text": "수은"
        },
        "502770": {
            "id": 502770,
            "text": ""
        },
        "502769": {
            "id": 502769,
            "text": "장미 효과 증가"
        },
        "502589": {
            "id": 502589,
            "text": "hakusai"
        },
        "502595": {
            "id": 502595,
            "text": "lunacle"
        },
        "502766": {
            "id": 502766,
            "text": "꿈속의 마나<color=#00ff00>6</color>"
        },
        "502765": {
            "id": 502765,
            "text": "메인 스테이지 오픈"
        },
        "502764": {
            "id": 502764,
            "text": "던전 오픈"
        },
        "502763": {
            "id": 502763,
            "text": "제5장"
        },
        "502762": {
            "id": 502762,
            "text": "중간 세계"
        },
        "502761": {
            "id": 502761,
            "text": "제4장"
        },
        "502458": {
            "id": 502458,
            "text": "인형의 기본 코스튬."
        },
        "502459": {
            "id": 502459,
            "text": "수행이 끝난 미쿠, 캠퍼스에서 자신의 청춘을 즐기고 있다."
        },
        "502760": {
            "id": 502760,
            "text": "중간 세계"
        },
        "502461": {
            "id": 502461,
            "text": "바쁜 하루 일과를 마친 아르카나는 단골 술집에서 간단하게 한잔했다."
        },
        "502759": {
            "id": 502759,
            "text": "꿈속의 마나"
        },
        "502758": {
            "id": 502758,
            "text": "Lv.22오픈：스토리4.5-1"
        },
        "502757": {
            "id": 502757,
            "text": "Lv.20오픈：꿈속의 마나6"
        },
        "502756": {
            "id": 502756,
            "text": "Lv.15오픈：꿈속의 마나5"
        },
        "502755": {
            "id": 502755,
            "text": "Lv.12오픈：스토리3.5-1"
        },
        "502754": {
            "id": 502754,
            "text": "Lv.10오픈：꿈속의 마나4"
        },
        "502753": {
            "id": 502753,
            "text": "Lv.5오픈：스토리2.5-1"
        },
        "502469": {
            "id": 502469,
            "text": "셔플은 바닷속을 헤엄치며 물고기들과 즐거운 시간을 보내고 있다."
        },
        "502752": {
            "id": 502752,
            "text": "Lv.4오픈：꿈속의 마나3"
        },
        "502471": {
            "id": 502471,
            "text": "중요한 제사 의식을 땡땡이 치고 몰래 해변으로 놀러 간 유타야는 친구들과 행복한 시간을 보내고 있다."
        },
        "502751": {
            "id": 502751,
            "text": "창술 효과 증가"
        },
        "502750": {
            "id": 502750,
            "text": "파마 효과 증가"
        },
        "502749": {
            "id": 502749,
            "text": "당신만의 아이돌"
        },
        "502748": {
            "id": 502748,
            "text": "겨울연가"
        },
        "502747": {
            "id": 502747,
            "text": "고귀한 혈맥"
        },
        "502746": {
            "id": 502746,
            "text": "프라마닉스"
        },
        "502745": {
            "id": 502745,
            "text": "명절 축전"
        },
        "502744": {
            "id": 502744,
            "text": "관중은 한 명 뿐이지만, 한 명이면 된다. 당신만을 위해, 한 사람만을 위해 사랑 노래를 부른다."
        },
        "502743": {
            "id": 502743,
            "text": "유행하는 옷으로 갈아입고 마음에 둔 사람을 초대해서 함께 성수를 타고 하늘을 날아다닌다."
        },
        "502742": {
            "id": 502742,
            "text": "자신의 행동이 고귀한 신분에 어울리지 않는다는 것을 깨닫고 바꾸기로 마음먹었다."
        },
        "502741": {
            "id": 502741,
            "text": "처음으로 본 흩날리는 눈송이에 추위도 잊고 한껏 들떠서 놀았다."
        },
        "502740": {
            "id": 502740,
            "text": "1년 중 가장 중요한 의식을 위해 정성껏 치장을 하고 마음껏 기념일을 즐긴다."
        },
        "502739": {
            "id": 502739,
            "text": "달의 비호 효과 증가"
        },
        "502738": {
            "id": 502738,
            "text": "만월 효과 증가"
        },
        "502737": {
            "id": 502737,
            "text": "달의 의식 효과 증가"
        },
        "502736": {
            "id": 502736,
            "text": "허공의 힘 효과 증가"
        },
        "502735": {
            "id": 502735,
            "text": "피의 저주 효과 증가"
        },
        "502734": {
            "id": 502734,
            "text": "음성"
        },
        "502733": {
            "id": 502733,
            "text": "배경 스토리"
        },
        "502732": {
            "id": 502732,
            "text": "캐릭터 정보"
        },
        "502731": {
            "id": 502731,
            "text": "일러스트"
        },
        "502730": {
            "id": 502730,
            "text": "성우"
        },
        "502729": {
            "id": 502729,
            "text": "취향"
        },
        "502728": {
            "id": 502728,
            "text": "출신"
        },
        "502727": {
            "id": 502727,
            "text": "생일"
        },
        "502726": {
            "id": 502726,
            "text": "종족"
        },
        "502725": {
            "id": 502725,
            "text": "신장"
        },
        "502724": {
            "id": 502724,
            "text": "연령"
        },
        "502723": {
            "id": 502723,
            "text": "성별"
        },
        "502722": {
            "id": 502722,
            "text": "$parameter1$의 선물"
        },
        "502721": {
            "id": 502721,
            "text": "인연 Lv.$parameter1$ 오픈"
        },
        "502720": {
            "id": 502720,
            "text": "스토리4"
        },
        "502719": {
            "id": 502719,
            "text": "스토리3"
        },
        "502718": {
            "id": 502718,
            "text": "스토리2"
        },
        "502717": {
            "id": 502717,
            "text": "스토리1"
        },
        "502715": {
            "id": 502715,
            "text": "첫 결제 시 획득"
        },
        "502714": {
            "id": 502714,
            "text": "선글라스를 쓴 마녀"
        },
        "502713": {
            "id": 502713,
            "text": "멋진 선글라스"
        },
        "502712": {
            "id": 502712,
            "text": "인연 음성IV 오픈"
        },
        "502711": {
            "id": 502711,
            "text": "인연 음성III 오픈"
        },
        "502710": {
            "id": 502710,
            "text": "인연 음성II 오픈"
        },
        "502709": {
            "id": 502709,
            "text": "인연 음성I 오픈"
        },
        "502708": {
            "id": 502708,
            "text": "배경 스토리Ⅳ 오픈"
        },
        "502707": {
            "id": 502707,
            "text": "배경 스토리Ⅲ 오픈"
        },
        "502706": {
            "id": 502706,
            "text": "배경 스토리Ⅱ 오픈"
        },
        "502705": {
            "id": 502705,
            "text": "배경 스토리Ⅰ 오픈"
        },
        "502704": {
            "id": 502704,
            "text": "주는 최대 마법 피해"
        },
        "502703": {
            "id": 502703,
            "text": "주는 최대 물리 피해"
        },
        "502700": {
            "id": 502700,
            "text": "2스킬 협동 확률"
        },
        "502699": {
            "id": 502699,
            "text": "1스킬 협동 확률"
        },
        "502685": {
            "id": 502685,
            "text": "물리 방어 강화Ⅱ 기본 물리 방어 3% 증가"
        },
        "502684": {
            "id": 502684,
            "text": "HP 강화Ⅱ 기본 최대 HP 3% 증가"
        },
        "502683": {
            "id": 502683,
            "text": "물리 방어 강화Ⅰ 기본 물리 방어 2% 증가"
        },
        "502682": {
            "id": 502682,
            "text": "HP 강화Ⅰ 기본 최대 HP 2% 증가"
        },
        "502681": {
            "id": 502681,
            "text": "마법 방어 강화Ⅱ 기본 마법 방어 3% 증가"
        },
        "502680": {
            "id": 502680,
            "text": "HP 강화Ⅱ 기본 최대 HP 3% 증가"
        },
        "502679": {
            "id": 502679,
            "text": "마법 방어 강화Ⅰ 기본 마법 방어 2% 증가"
        },
        "502678": {
            "id": 502678,
            "text": "HP 강화Ⅰ 기본 최대 HP 2% 증가"
        },
        "502677": {
            "id": 502677,
            "text": "공격 강화Ⅱ 기본 공격력 3% 증가"
        },
        "502676": {
            "id": 502676,
            "text": "HP 강화Ⅱ 기본 최대 HP 3% 증가"
        },
        "502675": {
            "id": 502675,
            "text": "공격 강화Ⅰ 기본 공격력 2% 증가"
        },
        "502674": {
            "id": 502674,
            "text": "HP 강화Ⅰ 기본 최대 HP 2% 증가"
        },
        "502673": {
            "id": 502673,
            "text": "공격 강화Ⅱ 기본 공격력 3% 증가"
        },
        "502672": {
            "id": 502672,
            "text": "HP 강화Ⅱ 기본 최대 HP 3% 증가"
        },
        "502536": {
            "id": 502536,
            "text": "不可燃物"
        },
        "502537": {
            "id": 502537,
            "text": "彩阳"
        },
        "502538": {
            "id": 502538,
            "text": "幻象黑兔"
        },
        "502539": {
            "id": 502539,
            "text": "welchino"
        },
        "502671": {
            "id": 502671,
            "text": "공격 강화Ⅰ 기본 공격력 2% 증가"
        },
        "502670": {
            "id": 502670,
            "text": "HP 강화Ⅰ 기본 최대 HP 2% 증가"
        },
        "502542": {
            "id": 502542,
            "text": "影法师"
        },
        "502669": {
            "id": 502669,
            "text": "마법 방어 강화Ⅱ 기본 마법 방어 3% 증가"
        },
        "502544": {
            "id": 502544,
            "text": "渡辺明夫"
        },
        "502545": {
            "id": 502545,
            "text": "Kurot"
        },
        "502668": {
            "id": 502668,
            "text": "HP 강화Ⅱ 기본 최대 HP 3% 증가"
        },
        "502547": {
            "id": 502547,
            "text": "幻象黑兔"
        },
        "502548": {
            "id": 502548,
            "text": "snow_is"
        },
        "502667": {
            "id": 502667,
            "text": "마법 방어 강화Ⅰ 기본 마법 방어 2% 증가"
        },
        "502666": {
            "id": 502666,
            "text": "HP 강화Ⅰ 기본 최대 HP 2% 증가"
        },
        "502551": {
            "id": 502551,
            "text": "PHI"
        },
        "502552": {
            "id": 502552,
            "text": "戏言咸咸"
        },
        "502633": {
            "id": 502633,
            "text": "돌파4에 오픈"
        },
        "502554": {
            "id": 502554,
            "text": "剑风"
        },
        "502630": {
            "id": 502630,
            "text": "인형의 돌파 코스튬."
        },
        "502556": {
            "id": 502556,
            "text": "amatou"
        },
        "502629": {
            "id": 502629,
            "text": "돌파 코스튬"
        },
        "502558": {
            "id": 502558,
            "text": "るび様"
        },
        "502628": {
            "id": 502628,
            "text": "이벤트 획득"
        },
        "502627": {
            "id": 502627,
            "text": "상점 구매"
        },
        "502561": {
            "id": 502561,
            "text": "mitha"
        },
        "502562": {
            "id": 502562,
            "text": "观月诗乃"
        },
        "502624": {
            "id": 502624,
            "text": "마터웨이브"
        },
        "502564": {
            "id": 502564,
            "text": "？"
        },
        "502623": {
            "id": 502623,
            "text": "모티머"
        },
        "502566": {
            "id": 502566,
            "text": "姬乃"
        },
        "502622": {
            "id": 502622,
            "text": "페이"
        },
        "502621": {
            "id": 502621,
            "text": "힐다"
        },
        "502620": {
            "id": 502620,
            "text": "루다"
        },
        "502619": {
            "id": 502619,
            "text": "청색이동 관측자"
        },
        "502618": {
            "id": 502618,
            "text": "장미의 마음"
        },
        "502617": {
            "id": 502617,
            "text": "관통하는 창"
        },
        "502616": {
            "id": 502616,
            "text": "왕실의 검"
        },
        "502615": {
            "id": 502615,
            "text": "별빛을 모으는 자"
        },
        "502575": {
            "id": 502575,
            "text": "nano"
        },
        "502614": {
            "id": 502614,
            "text": "EX"
        },
        "502577": {
            "id": 502577,
            "text": "猫锅仓"
        },
        "502611": {
            "id": 502611,
            "text": "ささきむつみ"
        },
        "502607": {
            "id": 502607,
            "text": "Alov"
        },
        "502580": {
            "id": 502580,
            "text": "nennen"
        },
        "502600": {
            "id": 502600,
            "text": "狗神煌"
        },
        "502582": {
            "id": 502582,
            "text": "feng"
        },
        "502596": {
            "id": 502596,
            "text": "弯弯向东流"
        },
        "502584": {
            "id": 502584,
            "text": "Sola"
        },
        "501561": {
            "id": 501561,
            "text": "HP 강화Ⅰ HP +50"
        },
        "501562": {
            "id": 501562,
            "text": "HP 강화Ⅱ HP +100"
        },
        "501563": {
            "id": 501563,
            "text": "HP 강화Ⅲ HP +150"
        },
        "501564": {
            "id": 501564,
            "text": "HP 강화Ⅳ HP +200"
        },
        "501565": {
            "id": 501565,
            "text": "공격 강화Ⅰ 공격 +10"
        },
        "501566": {
            "id": 501566,
            "text": "공격 강화Ⅱ 공격 +20"
        },
        "501567": {
            "id": 501567,
            "text": "공격 강화Ⅲ 공격 +30"
        },
        "501568": {
            "id": 501568,
            "text": "공격 강화Ⅳ 공격 +50"
        },
        "501569": {
            "id": 501569,
            "text": "물리 방어 강화Ⅰ 물리 방어 +20"
        },
        "501570": {
            "id": 501570,
            "text": "물리 방어 강화Ⅱ 물리 방어 +40"
        },
        "501571": {
            "id": 501571,
            "text": "물리 방어 강화Ⅲ 물리 방어 +60"
        },
        "501572": {
            "id": 501572,
            "text": "물리 방어 강화Ⅳ 물리 방어 +100"
        },
        "501573": {
            "id": 501573,
            "text": "마법 방어 강화Ⅰ 마법 방어 +20"
        },
        "501574": {
            "id": 501574,
            "text": "마법 방어 강화Ⅱ 마법 방어 +40"
        },
        "501575": {
            "id": 501575,
            "text": "마법 방어 강화Ⅲ 마법 방어 +60"
        },
        "501576": {
            "id": 501576,
            "text": "마법 방어 강화Ⅳ 마법 방어 +100"
        },
        "501577": {
            "id": 501577,
            "text": "치명타 강화Ⅰ 치명타 레벨 +400"
        },
        "501578": {
            "id": 501578,
            "text": "치명타 강화Ⅱ 치명타 레벨 +800"
        },
        "501579": {
            "id": 501579,
            "text": "치명타 강화Ⅲ 치명타 레벨 +1200"
        },
        "501580": {
            "id": 501580,
            "text": "치명타 강화Ⅳ 치명타 레벨 +1600"
        },
        "501581": {
            "id": 501581,
            "text": "영혼 인장1 효과 상승"
        },
        "501582": {
            "id": 501582,
            "text": "영혼 인장2 효과 상승"
        },
        "501583": {
            "id": 501583,
            "text": "영혼 인장3 효과 상승"
        },
        "501584": {
            "id": 501584,
            "text": "$heroine$"
        },
        "501585": {
            "id": 501585,
            "text": "크로쉐"
        },
        "501586": {
            "id": 501586,
            "text": "미쿠"
        },
        "501587": {
            "id": 501587,
            "text": "에우랄리아"
        },
        "501588": {
            "id": 501588,
            "text": "유토"
        },
        "501589": {
            "id": 501589,
            "text": "베데어"
        },
        "501590": {
            "id": 501590,
            "text": "바루브"
        },
        "501591": {
            "id": 501591,
            "text": "아발렌"
        },
        "501592": {
            "id": 501592,
            "text": "프리뮬라"
        },
        "501593": {
            "id": 501593,
            "text": "포크로어"
        },
        "501594": {
            "id": 501594,
            "text": "칼레도니아"
        },
        "501595": {
            "id": 501595,
            "text": "아네모네"
        },
        "501596": {
            "id": 501596,
            "text": "아카샤"
        },
        "501597": {
            "id": 501597,
            "text": "네메시"
        },
        "501598": {
            "id": 501598,
            "text": "파카네"
        },
        "501599": {
            "id": 501599,
            "text": "옥타비아"
        },
        "501600": {
            "id": 501600,
            "text": "엘라"
        },
        "501601": {
            "id": 501601,
            "text": "타마"
        },
        "501602": {
            "id": 501602,
            "text": "미코토"
        },
        "501603": {
            "id": 501603,
            "text": "하델"
        },
        "501604": {
            "id": 501604,
            "text": "스발바드"
        },
        "501605": {
            "id": 501605,
            "text": "굴베이그"
        },
        "501606": {
            "id": 501606,
            "text": "캐서린"
        },
        "501607": {
            "id": 501607,
            "text": "체르니"
        },
        "501608": {
            "id": 501608,
            "text": "다시오스"
        },
        "501609": {
            "id": 501609,
            "text": "루시아"
        },
        "501610": {
            "id": 501610,
            "text": "케테스"
        },
        "501611": {
            "id": 501611,
            "text": "바이올라"
        },
        "501612": {
            "id": 501612,
            "text": "세라냐"
        },
        "501613": {
            "id": 501613,
            "text": "아르카나"
        },
        "501614": {
            "id": 501614,
            "text": "파르페"
        },
        "501615": {
            "id": 501615,
            "text": "이리스"
        },
        "501616": {
            "id": 501616,
            "text": "시네티아"
        },
        "501617": {
            "id": 501617,
            "text": "셔플"
        },
        "501618": {
            "id": 501618,
            "text": "릴리아"
        },
        "501619": {
            "id": 501619,
            "text": "루즈"
        },
        "501620": {
            "id": 501620,
            "text": "루소니아"
        },
        "501621": {
            "id": 501621,
            "text": "메타모포스"
        },
        "501622": {
            "id": 501622,
            "text": "라판"
        },
        "501623": {
            "id": 501623,
            "text": "마리나"
        },
        "501624": {
            "id": 501624,
            "text": "우스피아"
        },
        "501625": {
            "id": 501625,
            "text": "아케론테"
        },
        "501626": {
            "id": 501626,
            "text": "노른"
        },
        "501627": {
            "id": 501627,
            "text": "파르메"
        },
        "501628": {
            "id": 501628,
            "text": "콜리타로"
        },
        "501629": {
            "id": 501629,
            "text": "다나"
        },
        "501630": {
            "id": 501630,
            "text": "녹투르나"
        },
        "501631": {
            "id": 501631,
            "text": "키폰"
        },
        "501632": {
            "id": 501632,
            "text": "유루구"
        },
        "501633": {
            "id": 501633,
            "text": "아빌"
        },
        "501634": {
            "id": 501634,
            "text": "투오넬"
        },
        "501635": {
            "id": 501635,
            "text": "유타야"
        },
        "501636": {
            "id": 501636,
            "text": "아르디시아"
        },
        "501637": {
            "id": 501637,
            "text": "가르디티스"
        },
        "501638": {
            "id": 501638,
            "text": "안&네로"
        },
        "501639": {
            "id": 501639,
            "text": "아마나미"
        },
        "501640": {
            "id": 501640,
            "text": "코타나"
        },
        "501641": {
            "id": 501641,
            "text": "베랄"
        },
        "501642": {
            "id": 501642,
            "text": "루안"
        },
        "501643": {
            "id": 501643,
            "text": "카무이"
        },
        "501644": {
            "id": 501644,
            "text": "유이"
        },
        "501645": {
            "id": 501645,
            "text": "나사"
        },
        "501646": {
            "id": 501646,
            "text": "난나르"
        },
        "501647": {
            "id": 501647,
            "text": "이사벨라"
        },
        "501648": {
            "id": 501648,
            "text": "라 크리마"
        },
        "501649": {
            "id": 501649,
            "text": "하은"
        },
        "501650": {
            "id": 501650,
            "text": "애시크로프트"
        },
        "501651": {
            "id": 501651,
            "text": "도린느"
        },
        "501652": {
            "id": 501652,
            "text": "마야우엘"
        },
        "501653": {
            "id": 501653,
            "text": "미나이어"
        },
        "501654": {
            "id": 501654,
            "text": "글라신"
        },
        "501655": {
            "id": 501655,
            "text": "샤르"
        },
        "501656": {
            "id": 501656,
            "text": "공허한 마녀"
        },
        "501657": {
            "id": 501657,
            "text": "시계탑의 시녀"
        },
        "501658": {
            "id": 501658,
            "text": "단마의 창"
        },
        "501659": {
            "id": 501659,
            "text": "루니아의 성녀"
        },
        "501660": {
            "id": 501660,
            "text": "허공의 마인"
        },
        "501661": {
            "id": 501661,
            "text": "정열의 춤"
        },
        "501662": {
            "id": 501662,
            "text": "달빛 늑대인간"
        },
        "501663": {
            "id": 501663,
            "text": "성령의 파수꾼"
        },
        "501664": {
            "id": 501664,
            "text": "꽃의 약사"
        },
        "501665": {
            "id": 501665,
            "text": "호수의 선율"
        },
        "501666": {
            "id": 501666,
            "text": "세상과 단절된 공주"
        },
        "501667": {
            "id": 501667,
            "text": "엘레멘탈리스트"
        },
        "501668": {
            "id": 501668,
            "text": "유성의 검희"
        },
        "501669": {
            "id": 501669,
            "text": "데스브링어"
        },
        "501670": {
            "id": 501670,
            "text": "서리의 마녀"
        },
        "501671": {
            "id": 501671,
            "text": "질풍의 검사"
        },
        "501672": {
            "id": 501672,
            "text": "용의 소녀"
        },
        "501673": {
            "id": 501673,
            "text": "신의 의지"
        },
        "501674": {
            "id": 501674,
            "text": "미오픈"
        },
        "501675": {
            "id": 501675,
            "text": "숙명을 좇는 무녀"
        },
        "501676": {
            "id": 501676,
            "text": "전장의 꽃"
        },
        "501677": {
            "id": 501677,
            "text": "복수의 맹세"
        },
        "501678": {
            "id": 501678,
            "text": "심연의 제물"
        },
        "501679": {
            "id": 501679,
            "text": "성스러운 기적"
        },
        "501680": {
            "id": 501680,
            "text": "기만의 천사"
        },
        "501681": {
            "id": 501681,
            "text": "균형의 집행자"
        },
        "501682": {
            "id": 501682,
            "text": "핏빛 시녀"
        },
        "501683": {
            "id": 501683,
            "text": "붉은 전희"
        },
        "501684": {
            "id": 501684,
            "text": "기계 인형 소녀"
        },
        "501685": {
            "id": 501685,
            "text": "질풍의 창궁"
        },
        "501686": {
            "id": 501686,
            "text": "운명을 점치는 자"
        },
        "501687": {
            "id": 501687,
            "text": "성령의 징벌자"
        },
        "501688": {
            "id": 501688,
            "text": "숲의 여왕"
        },
        "501689": {
            "id": 501689,
            "text": "고통의 찬가"
        },
        "501690": {
            "id": 501690,
            "text": "존재의 말살자"
        },
        "501691": {
            "id": 501691,
            "text": "오로라 공주"
        },
        "501692": {
            "id": 501692,
            "text": "광란의 붉은 눈동자"
        },
        "501693": {
            "id": 501693,
            "text": "날카로운 발톱의 파수꾼"
        },
        "501694": {
            "id": 501694,
            "text": "영혼의 조종자"
        },
        "501695": {
            "id": 501695,
            "text": "숙명의 발톱"
        },
        "501696": {
            "id": 501696,
            "text": "인형사"
        },
        "501697": {
            "id": 501697,
            "text": "사막의 여왕"
        },
        "501698": {
            "id": 501698,
            "text": "망령을 노래하는 자"
        },
        "501699": {
            "id": 501699,
            "text": "영원의 신관"
        },
        "501700": {
            "id": 501700,
            "text": "진리의 탐구자"
        },
        "501701": {
            "id": 501701,
            "text": "대지의 은혜"
        },
        "501702": {
            "id": 501702,
            "text": "호수의 여신"
        },
        "501703": {
            "id": 501703,
            "text": "선홍의 달"
        },
        "501704": {
            "id": 501704,
            "text": "명계의 안내자"
        },
        "501705": {
            "id": 501705,
            "text": "허공의 관"
        },
        "501706": {
            "id": 501706,
            "text": "왕궁의 수위"
        },
        "501707": {
            "id": 501707,
            "text": "혼혈 치유사"
        },
        "501708": {
            "id": 501708,
            "text": "작은 치유사"
        },
        "501709": {
            "id": 501709,
            "text": "해변을 거니는 자"
        },
        "501710": {
            "id": 501710,
            "text": "낙원의 시인"
        },
        "501711": {
            "id": 501711,
            "text": "쌍둥이 집행자"
        },
        "501712": {
            "id": 501712,
            "text": "빛의 공주"
        },
        "501713": {
            "id": 501713,
            "text": "결재자"
        },
        "501714": {
            "id": 501714,
            "text": "어둠의 집사"
        },
        "501715": {
            "id": 501715,
            "text": "붉은 깃털의 봉황"
        },
        "501716": {
            "id": 501716,
            "text": "한낮의 아이"
        },
        "501717": {
            "id": 501717,
            "text": "파마의 창"
        },
        "501718": {
            "id": 501718,
            "text": "희대의 마법사"
        },
        "501719": {
            "id": 501719,
            "text": "거울의 파수꾼"
        },
        "501720": {
            "id": 501720,
            "text": "신의 대행자"
        },
        "501721": {
            "id": 501721,
            "text": "보석의 눈물"
        },
        "501722": {
            "id": 501722,
            "text": "환상세계의 토끼"
        },
        "501723": {
            "id": 501723,
            "text": "퇴마검"
        },
        "501724": {
            "id": 501724,
            "text": "신의 선물"
        },
        "501725": {
            "id": 501725,
            "text": "나무의 은혜"
        },
        "501726": {
            "id": 501726,
            "text": "밤의 가호"
        },
        "501727": {
            "id": 501727,
            "text": "전염병 의사"
        },
        "501728": {
            "id": 501728,
            "text": "운명을 기다리는 자"
        },
        "501729": {
            "id": 501729,
            "text": "현재 HP"
        },
        "501730": {
            "id": 501730,
            "text": "HP"
        },
        "501731": {
            "id": 501731,
            "text": "공격"
        },
        "501732": {
            "id": 501732,
            "text": "공격"
        },
        "501733": {
            "id": 501733,
            "text": "물리 방어"
        },
        "501734": {
            "id": 501734,
            "text": "마법 방어"
        },
        "501735": {
            "id": 501735,
            "text": "속도"
        },
        "501736": {
            "id": 501736,
            "text": "이번 공격의 피해"
        },
        "501737": {
            "id": 501737,
            "text": "물리 피해 증가"
        },
        "501738": {
            "id": 501738,
            "text": "물리 피해 감소"
        },
        "501739": {
            "id": 501739,
            "text": "마법 피해 증가"
        },
        "501740": {
            "id": 501740,
            "text": "마법 피해 감소"
        },
        "501741": {
            "id": 501741,
            "text": "치명타율"
        },
        "501742": {
            "id": 501742,
            "text": "치명타 위력"
        },
        "502767": {
            "id": 502767,
            "text": "생존 마스터 효과 증가"
        },
        "502768": {
            "id": 502768,
            "text": "공격 마스터 효과 증가"
        },
        "501745": {
            "id": 501745,
            "text": "공격 속도"
        },
        "501746": {
            "id": 501746,
            "text": "회피율"
        },
        "501747": {
            "id": 501747,
            "text": "물리 흡혈"
        },
        "501748": {
            "id": 501748,
            "text": "마법 흡혈"
        },
        "501749": {
            "id": 501749,
            "text": "물리 막기"
        },
        "501750": {
            "id": 501750,
            "text": "마법 막기"
        },
        "501751": {
            "id": 501751,
            "text": "받는 피해량"
        },
        "501752": {
            "id": 501752,
            "text": "마법 회피율"
        },
        "501753": {
            "id": 501753,
            "text": "물리 관통"
        },
        "501754": {
            "id": 501754,
            "text": "마법 관통"
        },
        "501755": {
            "id": 501755,
            "text": "치명타 저항"
        },
        "502780": {
            "id": 502780,
            "text": "이 언니 너무 대단해요."
        },
        "501757": {
            "id": 501757,
            "text": "추가 물리 피해"
        },
        "501758": {
            "id": 501758,
            "text": "추가 마법 피해"
        },
        "501759": {
            "id": 501759,
            "text": "받는 치료 효과 버프"
        }
    },
    "AllIds": [
        501561,
        501562,
        501563,
        501564,
        501565,
        501566,
        501567,
        501568,
        501569,
        501570,
        501571,
        501572,
        501573,
        501574,
        501575,
        501576,
        501577,
        501578,
        501579,
        501580,
        501581,
        501582,
        501583,
        501584,
        501585,
        501586,
        501587,
        501588,
        501589,
        501590,
        501591,
        501592,
        501593,
        501594,
        501595,
        501596,
        501597,
        501598,
        501599,
        501600,
        501601,
        501602,
        501603,
        501604,
        501605,
        501606,
        501607,
        501608,
        501609,
        501610,
        501611,
        501612,
        501613,
        501614,
        501615,
        501616,
        501617,
        501618,
        501619,
        501620,
        501621,
        501622,
        501623,
        501624,
        501625,
        501626,
        501627,
        501628,
        501629,
        501630,
        501631,
        501632,
        501633,
        501634,
        501635,
        501636,
        501637,
        501638,
        501639,
        501640,
        501641,
        501642,
        501643,
        501644,
        501645,
        501646,
        501647,
        501648,
        501649,
        501650,
        501651,
        501652,
        501653,
        501654,
        501655,
        501656,
        501657,
        501658,
        501659,
        501660,
        501661,
        501662,
        501663,
        501664,
        501665,
        501666,
        501667,
        501668,
        501669,
        501670,
        501671,
        501672,
        501673,
        501674,
        501675,
        501676,
        501677,
        501678,
        501679,
        501680,
        501681,
        501682,
        501683,
        501684,
        501685,
        501686,
        501687,
        501688,
        501689,
        501690,
        501691,
        501692,
        501693,
        501694,
        501695,
        501696,
        501697,
        501698,
        501699,
        501700,
        501701,
        501702,
        501703,
        501704,
        501705,
        501706,
        501707,
        501708,
        501709,
        501710,
        501711,
        501712,
        501713,
        501714,
        501715,
        501716,
        501717,
        501718,
        501719,
        501720,
        501721,
        501722,
        501723,
        501724,
        501725,
        501726,
        501727,
        501728,
        501729,
        501730,
        501731,
        501732,
        501733,
        501734,
        501735,
        501736,
        501737,
        501738,
        501739,
        501740,
        501741,
        501742,
        501745,
        501746,
        501747,
        501748,
        501749,
        501750,
        501751,
        501752,
        501753,
        501754,
        501755,
        501757,
        501758,
        501759,
        501760,
        501761,
        501762,
        501763,
        501764,
        501765,
        501766,
        501767,
        501768,
        501769,
        501770,
        501771,
        501772,
        501773,
        501774,
        501775,
        501776,
        501777,
        501778,
        501779,
        501780,
        501781,
        501782,
        501783,
        501784,
        501785,
        501786,
        501787,
        501788,
        501789,
        501790,
        501791,
        501792,
        501793,
        501794,
        501795,
        501796,
        501797,
        501798,
        501799,
        501800,
        501801,
        501802,
        501803,
        501804,
        501805,
        501806,
        501807,
        501808,
        501809,
        501810,
        501811,
        501812,
        501813,
        501814,
        501815,
        501816,
        501817,
        501818,
        501827,
        501828,
        501829,
        501830,
        501831,
        501832,
        501833,
        501834,
        501835,
        501836,
        501837,
        501838,
        501839,
        501840,
        501841,
        501842,
        501852,
        501853,
        501854,
        501855,
        501856,
        501857,
        501858,
        501859,
        501860,
        501864,
        501865,
        501866,
        501867,
        501868,
        501869,
        501870,
        501871,
        501872,
        501873,
        501874,
        501875,
        501876,
        501877,
        501878,
        501879,
        501880,
        501882,
        501883,
        501884,
        501885,
        501886,
        501887,
        501888,
        501889,
        501890,
        501891,
        501892,
        501893,
        501894,
        501895,
        501896,
        501897,
        501898,
        501899,
        501900,
        501901,
        501902,
        501903,
        501904,
        501905,
        501906,
        501907,
        501908,
        501909,
        501910,
        501911,
        501912,
        501913,
        501914,
        501915,
        501916,
        501917,
        501918,
        501919,
        501920,
        501921,
        501923,
        501924,
        501925,
        501926,
        501927,
        501929,
        501930,
        501931,
        501932,
        501933,
        501934,
        501935,
        501936,
        501937,
        501938,
        501939,
        501940,
        501941,
        501942,
        501943,
        501944,
        501945,
        501946,
        501947,
        501948,
        501949,
        501950,
        501951,
        501952,
        501953,
        501954,
        501955,
        501956,
        501957,
        502377,
        502378,
        502379,
        502380,
        502381,
        502382,
        502383,
        502384,
        502458,
        502459,
        502461,
        502469,
        502471,
        502536,
        502537,
        502538,
        502539,
        502542,
        502544,
        502545,
        502547,
        502548,
        502551,
        502552,
        502554,
        502556,
        502558,
        502561,
        502562,
        502564,
        502566,
        502575,
        502577,
        502580,
        502582,
        502584,
        502585,
        502589,
        502595,
        502596,
        502600,
        502607,
        502611,
        502614,
        502615,
        502616,
        502617,
        502618,
        502619,
        502620,
        502621,
        502622,
        502623,
        502624,
        502627,
        502628,
        502629,
        502630,
        502633,
        502666,
        502667,
        502668,
        502669,
        502670,
        502671,
        502672,
        502673,
        502674,
        502675,
        502676,
        502677,
        502678,
        502679,
        502680,
        502681,
        502682,
        502683,
        502684,
        502685,
        502699,
        502700,
        502703,
        502704,
        502705,
        502706,
        502707,
        502708,
        502709,
        502710,
        502711,
        502712,
        502713,
        502714,
        502715,
        502717,
        502718,
        502719,
        502720,
        502721,
        502722,
        502723,
        502724,
        502725,
        502726,
        502727,
        502728,
        502729,
        502730,
        502731,
        502732,
        502733,
        502734,
        502735,
        502736,
        502737,
        502738,
        502739,
        502740,
        502741,
        502742,
        502743,
        502744,
        502745,
        502746,
        502747,
        502748,
        502749,
        502750,
        502751,
        502752,
        502753,
        502754,
        502755,
        502756,
        502757,
        502758,
        502759,
        502760,
        502761,
        502762,
        502763,
        502764,
        502765,
        502766,
        502767,
        502768,
        502769,
        502770,
        502771,
        502772,
        502773,
        502774,
        502775,
        502776,
        502777,
        502778,
        502779,
        502780,
        502781,
        502782,
        502783,
        502784,
        502785,
        502786,
        502787,
        502788,
        502789,
        502790,
        502791,
        502792,
        502793,
        502794,
        502795,
        502796,
        502797,
        502798,
        502799,
        502800,
        502801,
        502802,
        502803,
        502804,
        502805,
        502806,
        502807,
        502808,
        502809,
        502810,
        502811,
        502812,
        502813,
        502814,
        502815,
        502816
    ]
}